umcp/__init__.py
umcp/__main__.py
umcp/api_umcp.py
umcp/cli.py
umcp/closures.py
umcp/compute_utils.py
umcp/file_refs.py
umcp/frozen_contract.py
umcp/kernel_optimized.py
umcp/logging_utils.py
umcp/minimal_cli.py
umcp/py.typed
umcp/seam_optimized.py
umcp/ss1m_triad.py
umcp/umcp_extensions.py
umcp/uncertainty.py
umcp/validator.py
umcp-1.5.0.dist-info/licenses/LICENSE
umcp-1.5.0.dist-info/METADATA
umcp-1.5.0.dist-info/WHEEL
umcp-1.5.0.dist-info/entry_points.txt
umcp-1.5.0.dist-info/top_level.txt
umcp-1.5.0.dist-info/RECORD
