Metadata-Version: 2.4
Name: umcp
Version: 1.5.0
Summary: Universal Measurement Contract Protocol (UMCP): Production-grade contract-first validation framework with GCD and RCFT. Core Axiom: What Returns Through Collapse Is Real. Features bidirectional cross-references, closure registries, and full reproducibility.
Author: Clement Paulus
License-Expression: MIT
Project-URL: Homepage, https://github.com/calebpruett927/UMCP-Metadata-Runnable-Code
Project-URL: Repository, https://github.com/calebpruett927/UMCP-Metadata-Runnable-Code
Project-URL: Documentation, https://github.com/calebpruett927/UMCP-Metadata-Runnable-Code/blob/main/README.md
Project-URL: Issues, https://github.com/calebpruett927/UMCP-Metadata-Runnable-Code/issues
Project-URL: Changelog, https://github.com/calebpruett927/UMCP-Metadata-Runnable-Code/blob/main/CHANGELOG.md
Keywords: UMCP,GCD,RCFT,contract-first,validation,reproducibility,casepacks,fractal,recursive-field
Classifier: Development Status :: 4 - Beta
Classifier: Intended Audience :: Science/Research
Classifier: Programming Language :: Python :: 3
Classifier: Programming Language :: Python :: 3.11
Classifier: Programming Language :: Python :: 3.12
Classifier: Topic :: Scientific/Engineering
Classifier: Topic :: Software Development :: Quality Assurance
Classifier: Topic :: System :: Monitoring
Requires-Python: >=3.11
License-File: LICENSE
Requires-Dist: pyyaml>=6.0.1
Requires-Dist: jsonschema>=4.23.0
Requires-Dist: numpy>=1.24.0
Requires-Dist: scipy>=1.10.0
Provides-Extra: production
Requires-Dist: psutil>=5.9.0; extra == "production"
Provides-Extra: dev
Requires-Dist: pytest>=8.0.0; extra == "dev"
Requires-Dist: pytest-cov>=5.0.0; extra == "dev"
Requires-Dist: pytest-xdist>=3.8.0; extra == "dev"
Requires-Dist: ruff==0.5.0; extra == "dev"
Requires-Dist: mypy>=1.11.0; extra == "dev"
Requires-Dist: pre-commit>=3.8.0; extra == "dev"
Requires-Dist: psutil>=5.9.0; extra == "dev"
Requires-Dist: types-psutil>=6.0.0; extra == "dev"
Requires-Dist: fastapi>=0.109.0; extra == "dev"
Requires-Dist: httpx>=0.27.0; extra == "dev"
Provides-Extra: test
Requires-Dist: pytest>=8.0.0; extra == "test"
Requires-Dist: pytest-cov>=5.0.0; extra == "test"
Requires-Dist: pytest-xdist>=3.8.0; extra == "test"
Provides-Extra: api
Requires-Dist: fastapi>=0.109.0; extra == "api"
Requires-Dist: uvicorn[standard]>=0.27.0; extra == "api"
Provides-Extra: viz
Requires-Dist: streamlit>=1.30.0; extra == "viz"
Requires-Dist: pandas>=2.0.0; extra == "viz"
Requires-Dist: plotly>=5.18.0; extra == "viz"
Provides-Extra: communications
Requires-Dist: fastapi>=0.109.0; extra == "communications"
Requires-Dist: uvicorn[standard]>=0.27.0; extra == "communications"
Requires-Dist: streamlit>=1.30.0; extra == "communications"
Requires-Dist: pandas>=2.0.0; extra == "communications"
Requires-Dist: plotly>=5.18.0; extra == "communications"
Provides-Extra: all
Requires-Dist: pytest>=8.0.0; extra == "all"
Requires-Dist: pytest-cov>=5.0.0; extra == "all"
Requires-Dist: pytest-xdist>=3.8.0; extra == "all"
Requires-Dist: ruff>=0.5.0; extra == "all"
Requires-Dist: mypy>=1.11.0; extra == "all"
Requires-Dist: pre-commit>=3.8.0; extra == "all"
Requires-Dist: psutil>=5.9.0; extra == "all"
Requires-Dist: fastapi>=0.109.0; extra == "all"
Requires-Dist: uvicorn[standard]>=0.27.0; extra == "all"
Requires-Dist: streamlit>=1.30.0; extra == "all"
Requires-Dist: pandas>=2.0.0; extra == "all"
Requires-Dist: plotly>=5.18.0; extra == "all"
Dynamic: license-file
